processing/__init__.py
processing/data_processor.py
processing/functions.py
processing/readers.py
processing/utilities.py
streaming/__init__.py
streaming/cache.py
streaming/client.py
streaming/combined.py
streaming/compression.py
streaming/config.py
streaming/dataloader.py
streaming/dataset.py
streaming/downloader.py
streaming/item_loader.py
streaming/reader.py
streaming/resolver.py
streaming/sampler.py
streaming/serializers.py
streaming/shuffle.py
streaming/writer.py
utilities/__init__.py
utilities/broadcast.py
utilities/env.py
utilities/format.py
utilities/packing.py
utilities/shuffle.py
lightning_data-0.2.0.dev0.dist-info/LICENSE
lightning_data-0.2.0.dev0.dist-info/METADATA
lightning_data-0.2.0.dev0.dist-info/WHEEL
lightning_data-0.2.0.dev0.dist-info/top_level.txt
lightning_data-0.2.0.dev0.dist-info/RECORD
