Metadata-Version: 2.1
Name: lightning-data
Version: 0.2.0.dev0
Summary: The Deep Learning framework to train, deploy, and ship AI products Lightning fast.
Home-page: https://github.com/Lightning-AI/lit-data
Download-URL: https://github.com/Lightning-AI/lit-data
Author: Lightning AI et al.
Author-email: pytorch@lightning.ai
License: Apache-2.0
Project-URL: Bug Tracker, https://github.com/Lightning-AI/lit-data/issues
Project-URL: Documentation, https://lightning-ai.github.io/lit-data/
Project-URL: Source Code, https://github.com/Lightning-AI/lit-data
Keywords: deep learning,pytorch,AI
Classifier: Environment :: Console
Classifier: Natural Language :: English
Classifier: Development Status :: 3 - Alpha
Classifier: Intended Audience :: Developers
Classifier: Topic :: Scientific/Engineering :: Artificial Intelligence
Classifier: Topic :: Scientific/Engineering :: Information Analysis
Classifier: License :: OSI Approved :: Apache Software License
Classifier: Operating System :: OS Independent
Classifier: Programming Language :: Python :: 3
Classifier: Programming Language :: Python :: 3.10
Classifier: Programming Language :: Python :: 3.11
Classifier: Programming Language :: Python :: 3.12
Requires-Python: >=3.8
License-File: LICENSE
Requires-Dist: lightning-utilities <0.10.0,>=0.8.0
Requires-Dist: lightning-cloud ==0.5.64
Requires-Dist: torch <=2.2.0,>=2.1.0
Requires-Dist: filelock
Requires-Dist: tqdm
Requires-Dist: numpy
Requires-Dist: torchvision
Requires-Dist: pillow
